lmdiag/__init__.py
lmdiag/help.py
lmdiag/plots.py
lmdiag/style.py
lmdiag/statistics/__init__.py
lmdiag/statistics/base.py
lmdiag/statistics/linearmodels_stats.py
lmdiag/statistics/select.py
lmdiag/statistics/sklearn_stats.py
lmdiag/statistics/statsmodels_stats.py
lmdiag-0.4.1.dist-info/LICENSE
lmdiag-0.4.1.dist-info/METADATA
lmdiag-0.4.1.dist-info/WHEEL
lmdiag-0.4.1.dist-info/top_level.txt
lmdiag-0.4.1.dist-info/RECORD
