Metadata-Version: 2.1
Name: lmdiag
Version: 0.4.1
Summary: Diagnostic Plots for Lineare Regression Models. Similar to plot.lm in R.
Author-email: dynobo <dynobo@mailbox.org>
License: MIT
Project-URL: Homepage, http://github.com/dynobo/lmdiag
Keywords: lm,lineare,regression,diagnostics,plot,chart,linearmodels,statsmodels,scikit-learn
Classifier: Development Status :: 4 - Beta
Classifier: License :: OSI Approved :: MIT License
Classifier: Programming Language :: Python :: 3.10
Classifier: Programming Language :: Python :: 3.11
Classifier: Programming Language :: Python :: 3.12
Classifier: Programming Language :: Python :: 3.9
Classifier: Topic :: Scientific/Engineering :: Information Analysis
Requires-Python: >=3.9
License-File: LICENSE
Requires-Dist: matplotlib
Requires-Dist: numpy
Requires-Dist: scipy
Requires-Dist: statsmodels
Provides-Extra: dev
Requires-Dist: build ; extra == 'dev'
Requires-Dist: linearmodels ; extra == 'dev'
Requires-Dist: mypy ; extra == 'dev'
Requires-Dist: notebook ; extra == 'dev'
Requires-Dist: pre-commit ; extra == 'dev'
Requires-Dist: pytest ; extra == 'dev'
Requires-Dist: ruff ; extra == 'dev'
Requires-Dist: scikit-learn ; extra == 'dev'
